icsdscraper/PapaScrap.py
icsdscraper/__init__.py
icsdscraper/examples.py
icsdscraper/icsd_objects.py
icsdscraper-0.0.14.dist-info/METADATA
icsdscraper-0.0.14.dist-info/WHEEL
icsdscraper-0.0.14.dist-info/top_level.txt
icsdscraper-0.0.14.dist-info/RECORD
