Metadata-Version: 2.1
Name: icsdscraper
Version: 0.0.14
Summary: ICSD website scraper
Home-page: https://github.com/CheatModeON/icsd-scraper
Author: Achilleas Papakonstantinou
Author-email: achipap@hotmail.com
License: UNKNOWN
Platform: UNKNOWN
Classifier: Programming Language :: Python :: 3
Classifier: License :: OSI Approved :: MIT License
Classifier: Operating System :: OS Independent
Requires-Python: >=2.7
